{"packages":{"drupal\/charts_c3":{"3.0.0-alpha8":{"keywords":"Actively maintained,Content Display","homepage":"https:\/\/www.drupal.org\/project\/charts","version":"3.0.0-alpha8","version_normalized":"3.0.0.0-alpha8","license":"GPL-2.0-or-later","authors":[{"name":"Pierre.Vriens","homepage":"https:\/\/www.drupal.org\/user\/1689304"},{"name":"andileco","homepage":"https:\/\/www.drupal.org\/user\/2054544"},{"name":"brmassa","homepage":"https:\/\/www.drupal.org\/user\/67164"},{"name":"kenorb","homepage":"https:\/\/www.drupal.org\/user\/191974"},{"name":"quicksketch","homepage":"https:\/\/www.drupal.org\/user\/35821"},{"name":"rashad612","homepage":"https:\/\/www.drupal.org\/user\/319686"}],"support":{"source":"http:\/\/cgit.drupalcode.org\/charts"},"type":"metapackage","uid":"charts_c3-2950646","name":"drupal\/charts_c3","extra":{"branch-alias":{"dev-3.x":"3.x-dev"},"drupal":{"version":"8.x-3.0-alpha8","datestamp":"1520396285","security-coverage":{"status":"not-covered","message":"Alpha releases are not covered by Drupal security advisories."}}},"description":"Charts module integration with C3 Charts.","require":{"drupal\/charts":"self.version","drupal\/core":"~8.0"}},"3.0.0-alpha7":{"keywords":"Actively maintained,Content Display","homepage":"https:\/\/www.drupal.org\/project\/charts","version":"0.0.1","version_normalized":"3.0.0.0-alpha7","license":"GPL-2.0-or-later","authors":[{"name":"Pierre.Vriens","homepage":"https:\/\/www.drupal.org\/user\/1689304"},{"name":"andileco","homepage":"https:\/\/www.drupal.org\/user\/2054544"},{"name":"brmassa","homepage":"https:\/\/www.drupal.org\/user\/67164"},{"name":"kenorb","homepage":"https:\/\/www.drupal.org\/user\/191974"},{"name":"quicksketch","homepage":"https:\/\/www.drupal.org\/user\/35821"},{"name":"rashad612","homepage":"https:\/\/www.drupal.org\/user\/319686"}],"support":{"source":"http:\/\/cgit.drupalcode.org\/charts"},"type":"metapackage","uid":"charts_c3-2926062","name":"drupal\/charts_c3","extra":{"branch-alias":{"dev-3.x":"3.x-dev"},"drupal":{"version":"8.x-3.0-alpha7","datestamp":"1520396285","security-coverage":{"status":"not-covered","message":"Alpha releases are not covered by Drupal security advisories."}},"assets":{"packages":{"dthree":"*","cthree":"*","cthree\/css":"*"}}},"description":"Charts module integration with C3 Charts.","require":{"drupal\/charts":"self.version","dthree":"*","cthree":"*","cthree\/css":"*","drupal\/core":"~8.0"},"repositories":[{"type":"package","package":{"name":"dthree","version":"3","type":"dthree","dist":{"url":"https:\/\/d3js.org\/d3.v3.min.js","type":"file"}}},{"type":"package","package":{"name":"cthree","version":"0.4.11","type":"cthree","dist":{"url":"https:\/\/cdnjs.cloudflare.com\/ajax\/libs\/c3\/0.4.11\/c3.min.js","type":"file"}}},{"type":"package","package":{"name":"cthree\/css","version":"0.4.11","type":"css","dist":{"url":"https:\/\/cdnjs.cloudflare.com\/ajax\/libs\/c3\/0.4.11\/c3.min.css","type":"file"}}}]},"3.0.0-alpha6":{"keywords":"Actively maintained,Content Display","homepage":"https:\/\/www.drupal.org\/project\/charts","version":"0.0.1","version_normalized":"3.0.0.0-alpha6","license":"GPL-2.0-or-later","authors":[{"name":"Pierre.Vriens","homepage":"https:\/\/www.drupal.org\/user\/1689304"},{"name":"andileco","homepage":"https:\/\/www.drupal.org\/user\/2054544"},{"name":"brmassa","homepage":"https:\/\/www.drupal.org\/user\/67164"},{"name":"kenorb","homepage":"https:\/\/www.drupal.org\/user\/191974"},{"name":"quicksketch","homepage":"https:\/\/www.drupal.org\/user\/35821"},{"name":"rashad612","homepage":"https:\/\/www.drupal.org\/user\/319686"}],"support":{"source":"http:\/\/cgit.drupalcode.org\/charts"},"type":"metapackage","uid":"charts_c3-2909806","name":"drupal\/charts_c3","extra":{"branch-alias":{"dev-3.x":"3.x-dev"},"drupal":{"version":"8.x-3.0-alpha6","datestamp":"1511536685","security-coverage":{"status":"not-covered","message":"Alpha releases are not covered by Drupal security advisories."}},"assets":{"packages":{"dthree":"*","cthree":"*","cthree\/css":"*"}}},"description":"Charts module integration with C3 Charts.","require":{"drupal\/charts":"self.version","dthree":"*","cthree":"*","cthree\/css":"*","drupal\/core":"~8.0"},"repositories":[{"type":"package","package":{"name":"dthree","version":"3","type":"dthree","dist":{"url":"https:\/\/d3js.org\/d3.v3.min.js","type":"file"}}},{"type":"package","package":{"name":"cthree","version":"0.4.11","type":"cthree","dist":{"url":"https:\/\/cdnjs.cloudflare.com\/ajax\/libs\/c3\/0.4.11\/c3.min.js","type":"file"}}},{"type":"package","package":{"name":"cthree\/css","version":"0.4.11","type":"css","dist":{"url":"https:\/\/cdnjs.cloudflare.com\/ajax\/libs\/c3\/0.4.11\/c3.min.css","type":"file"}}}]},"3.0.0-alpha5":{"keywords":"Actively maintained,Content Display","homepage":"https:\/\/www.drupal.org\/project\/charts","version":"0.0.1","version_normalized":"3.0.0.0-alpha5","license":"GPL-2.0-or-later","authors":[{"name":"Pierre.Vriens","homepage":"https:\/\/www.drupal.org\/user\/1689304"},{"name":"andileco","homepage":"https:\/\/www.drupal.org\/user\/2054544"},{"name":"brmassa","homepage":"https:\/\/www.drupal.org\/user\/67164"},{"name":"kenorb","homepage":"https:\/\/www.drupal.org\/user\/191974"},{"name":"quicksketch","homepage":"https:\/\/www.drupal.org\/user\/35821"},{"name":"rashad612","homepage":"https:\/\/www.drupal.org\/user\/319686"}],"support":{"source":"http:\/\/cgit.drupalcode.org\/charts"},"type":"metapackage","uid":"charts_c3-2898523","name":"drupal\/charts_c3","extra":{"branch-alias":{"dev-3.x":"3.x-dev"},"drupal":{"version":"8.x-3.0-alpha5","datestamp":"1505801644","security-coverage":{"status":"not-covered","message":"Alpha releases are not covered by Drupal security advisories."}},"assets":{"packages":{"dthree":"*","cthree":"*","cthree\/css":"*"}}},"description":"Charts module integration with C3 Charts.","require":{"drupal\/charts":"self.version","dthree":"*","cthree":"*","cthree\/css":"*","drupal\/core":"~8.0"},"repositories":[{"type":"package","package":{"name":"dthree","version":"3","type":"dthree","dist":{"url":"https:\/\/d3js.org\/d3.v3.min.js","type":"file"}}},{"type":"package","package":{"name":"cthree","version":"0.4.11","type":"cthree","dist":{"url":"https:\/\/cdnjs.cloudflare.com\/ajax\/libs\/c3\/0.4.11\/c3.min.js","type":"file"}}},{"type":"package","package":{"name":"cthree\/css","version":"0.4.11","type":"css","dist":{"url":"https:\/\/cdnjs.cloudflare.com\/ajax\/libs\/c3\/0.4.11\/c3.min.css","type":"file"}}}]},"3.0.0-alpha4":{"keywords":"Actively maintained,Content Display","homepage":"https:\/\/www.drupal.org\/project\/charts","version":"0.0.1","version_normalized":"3.0.0.0-alpha4","license":"GPL-2.0-or-later","authors":[{"name":"Pierre.Vriens","homepage":"https:\/\/www.drupal.org\/user\/1689304"},{"name":"andileco","homepage":"https:\/\/www.drupal.org\/user\/2054544"},{"name":"brmassa","homepage":"https:\/\/www.drupal.org\/user\/67164"},{"name":"kenorb","homepage":"https:\/\/www.drupal.org\/user\/191974"},{"name":"quicksketch","homepage":"https:\/\/www.drupal.org\/user\/35821"},{"name":"rashad612","homepage":"https:\/\/www.drupal.org\/user\/319686"}],"support":{"source":"http:\/\/cgit.drupalcode.org\/charts"},"type":"metapackage","uid":"charts_c3-2879506","name":"drupal\/charts_c3","extra":{"branch-alias":{"dev-3.x":"3.x-dev"},"drupal":{"version":"8.x-3.0-alpha4","datestamp":"1501473543","security-coverage":{"status":"not-covered","message":"Alpha releases are not covered by Drupal security advisories."}},"assets":{"packages":{"dthree":"*","cthree":"*","cthree\/css":"*"}}},"description":"Charts module integration with C3 Charts.","require":{"drupal\/charts":"self.version","dthree":"*","cthree":"*","cthree\/css":"*","drupal\/core":"~8.0"},"repositories":[{"type":"package","package":{"name":"dthree","version":"3","type":"dthree","dist":{"url":"https:\/\/d3js.org\/d3.v3.min.js","type":"file"}}},{"type":"package","package":{"name":"cthree","version":"0.4.11","type":"cthree","dist":{"url":"https:\/\/cdnjs.cloudflare.com\/ajax\/libs\/c3\/0.4.11\/c3.min.js","type":"file"}}},{"type":"package","package":{"name":"cthree\/css","version":"0.4.11","type":"css","dist":{"url":"https:\/\/cdnjs.cloudflare.com\/ajax\/libs\/c3\/0.4.11\/c3.min.css","type":"file"}}}]},"3.0.0-alpha3":{"keywords":"Actively maintained,Content Display","homepage":"https:\/\/www.drupal.org\/project\/charts","version":"0.0.1","version_normalized":"3.0.0.0-alpha3","license":"GPL-2.0-or-later","authors":[{"name":"Pierre.Vriens","homepage":"https:\/\/www.drupal.org\/user\/1689304"},{"name":"andileco","homepage":"https:\/\/www.drupal.org\/user\/2054544"},{"name":"brmassa","homepage":"https:\/\/www.drupal.org\/user\/67164"},{"name":"kenorb","homepage":"https:\/\/www.drupal.org\/user\/191974"},{"name":"quicksketch","homepage":"https:\/\/www.drupal.org\/user\/35821"},{"name":"rashad612","homepage":"https:\/\/www.drupal.org\/user\/319686"}],"support":{"source":"http:\/\/cgit.drupalcode.org\/charts"},"type":"metapackage","uid":"charts_c3-2872849","name":"drupal\/charts_c3","extra":{"branch-alias":{"dev-3.x":"3.x-dev"},"drupal":{"version":"8.x-3.0-alpha3","datestamp":"1495124289","security-coverage":{"status":"not-covered","message":"Alpha releases are not covered by Drupal security advisories."}},"assets":{"packages":{"dthree":"*","cthree":"*","cthree\/css":"*"}}},"description":"Charts module integration with C3 Charts.","require":{"drupal\/charts":"self.version","dthree":"*","cthree":"*","cthree\/css":"*","drupal\/core":"~8.0"},"repositories":[{"type":"package","package":{"name":"dthree","version":"3","type":"dthree","dist":{"url":"https:\/\/d3js.org\/d3.v3.min.js","type":"file"}}},{"type":"package","package":{"name":"cthree","version":"0.4.11","type":"cthree","dist":{"url":"https:\/\/cdnjs.cloudflare.com\/ajax\/libs\/c3\/0.4.11\/c3.min.js","type":"file"}}},{"type":"package","package":{"name":"cthree\/css","version":"0.4.11","type":"css","dist":{"url":"https:\/\/cdnjs.cloudflare.com\/ajax\/libs\/c3\/0.4.11\/c3.min.css","type":"file"}}}]},"3.0.0-alpha2":{"keywords":"Actively maintained,Content Display","homepage":"https:\/\/www.drupal.org\/project\/charts","version":"0.0.1","version_normalized":"3.0.0.0-alpha2","license":"GPL-2.0-or-later","authors":[{"name":"Pierre.Vriens","homepage":"https:\/\/www.drupal.org\/user\/1689304"},{"name":"andileco","homepage":"https:\/\/www.drupal.org\/user\/2054544"},{"name":"brmassa","homepage":"https:\/\/www.drupal.org\/user\/67164"},{"name":"kenorb","homepage":"https:\/\/www.drupal.org\/user\/191974"},{"name":"quicksketch","homepage":"https:\/\/www.drupal.org\/user\/35821"},{"name":"rashad612","homepage":"https:\/\/www.drupal.org\/user\/319686"}],"support":{"source":"http:\/\/cgit.drupalcode.org\/charts"},"type":"metapackage","uid":"charts_c3-2867760","name":"drupal\/charts_c3","extra":{"branch-alias":{"dev-3.x":"3.x-dev"},"drupal":{"version":"8.x-3.0-alpha2","datestamp":"1493181243","security-coverage":{"status":"not-covered","message":"Alpha releases are not covered by Drupal security advisories."}},"assets":{"packages":{"dthree":"*","cthree":"*","cthree\/css":"*"}}},"description":"Charts module integration with C3 Charts.","require":{"drupal\/charts":"self.version","dthree":"*","cthree":"*","cthree\/css":"*","drupal\/core":"~8.0"},"repositories":[{"type":"package","package":{"name":"dthree","version":"3","type":"dthree","dist":{"url":"https:\/\/d3js.org\/d3.v3.min.js","type":"file"}}},{"type":"package","package":{"name":"cthree","version":"0.4.11","type":"cthree","dist":{"url":"https:\/\/cdnjs.cloudflare.com\/ajax\/libs\/c3\/0.4.11\/c3.min.js","type":"file"}}},{"type":"package","package":{"name":"cthree\/css","version":"0.4.11","type":"css","dist":{"url":"https:\/\/cdnjs.cloudflare.com\/ajax\/libs\/c3\/0.4.11\/c3.min.css","type":"file"}}}]},"3.0.0-alpha1":{"keywords":"Actively maintained,Content Display","homepage":"https:\/\/www.drupal.org\/project\/charts","version":"0.0.1","version_normalized":"3.0.0.0-alpha1","license":"GPL-2.0-or-later","authors":[{"name":"Pierre.Vriens","homepage":"https:\/\/www.drupal.org\/user\/1689304"},{"name":"andileco","homepage":"https:\/\/www.drupal.org\/user\/2054544"},{"name":"brmassa","homepage":"https:\/\/www.drupal.org\/user\/67164"},{"name":"kenorb","homepage":"https:\/\/www.drupal.org\/user\/191974"},{"name":"quicksketch","homepage":"https:\/\/www.drupal.org\/user\/35821"},{"name":"rashad612","homepage":"https:\/\/www.drupal.org\/user\/319686"}],"support":{"source":"http:\/\/cgit.drupalcode.org\/charts"},"type":"metapackage","uid":"charts_c3-2862576","name":"drupal\/charts_c3","extra":{"branch-alias":{"dev-3.x":"3.x-dev"},"drupal":{"version":"8.x-3.0-alpha1","datestamp":"1491573484","security-coverage":{"status":"not-covered","message":"Alpha releases are not covered by Drupal security advisories."}},"assets":{"packages":{"dthree":"*","cthree":"*","cthree\/css":"*"}}},"description":"Charts module integration with C3 Charts.","require":{"drupal\/charts":"self.version","dthree":"*","cthree":"*","cthree\/css":"*","drupal\/core":"~8.0"},"repositories":[{"type":"package","package":{"name":"dthree","version":"3","type":"dthree","dist":{"url":"https:\/\/d3js.org\/d3.v3.min.js","type":"file"}}},{"type":"package","package":{"name":"cthree","version":"0.4.11","type":"cthree","dist":{"url":"https:\/\/cdnjs.cloudflare.com\/ajax\/libs\/c3\/0.4.11\/c3.min.js","type":"file"}}},{"type":"package","package":{"name":"cthree\/css","version":"0.4.11","type":"css","dist":{"url":"https:\/\/cdnjs.cloudflare.com\/ajax\/libs\/c3\/0.4.11\/c3.min.css","type":"file"}}}]},"dev-3.x":{"keywords":"Actively maintained,Content Display","homepage":"https:\/\/www.drupal.org\/project\/charts","version":"dev-3.x","version_normalized":"dev-3.x","license":"GPL-2.0-or-later","authors":[{"name":"Pierre.Vriens","homepage":"https:\/\/www.drupal.org\/user\/1689304"},{"name":"andileco","homepage":"https:\/\/www.drupal.org\/user\/2054544"},{"name":"brmassa","homepage":"https:\/\/www.drupal.org\/user\/67164"},{"name":"kenorb","homepage":"https:\/\/www.drupal.org\/user\/191974"},{"name":"quicksketch","homepage":"https:\/\/www.drupal.org\/user\/35821"},{"name":"rashad612","homepage":"https:\/\/www.drupal.org\/user\/319686"}],"support":{"source":"http:\/\/cgit.drupalcode.org\/charts"},"type":"metapackage","uid":"charts_c3-2861701","name":"drupal\/charts_c3","extra":{"branch-alias":{"dev-3.x":"3.x-dev"},"drupal":{"version":"8.x-3.0-alpha8+7-dev","datestamp":"1521732484","security-coverage":{"status":"not-covered","message":"Dev releases are not covered by Drupal security advisories."}}},"description":"Charts module integration with C3 Charts.","require":{"drupal\/charts":"self.version","drupal\/core":"~8.0"}},"dev-1.x":{"keywords":"Actively maintained,Content Display","homepage":"https:\/\/www.drupal.org\/project\/charts","version":"0.0.1","version_normalized":"dev-1.x","license":"GPL-2.0-or-later","authors":[{"name":"Pierre.Vriens","homepage":"https:\/\/www.drupal.org\/user\/1689304"},{"name":"andileco","homepage":"https:\/\/www.drupal.org\/user\/2054544"},{"name":"brmassa","homepage":"https:\/\/www.drupal.org\/user\/67164"},{"name":"kenorb","homepage":"https:\/\/www.drupal.org\/user\/191974"},{"name":"quicksketch","homepage":"https:\/\/www.drupal.org\/user\/35821"},{"name":"rashad612","homepage":"https:\/\/www.drupal.org\/user\/319686"}],"support":{"source":"http:\/\/cgit.drupalcode.org\/charts"},"type":"metapackage","uid":"charts_c3-2859295","name":"drupal\/charts_c3","extra":{"branch-alias":{"dev-1.x":"1.x-dev"},"drupal":{"version":"8.x-1.x-dev","datestamp":"1489243983","security-coverage":{"status":"not-covered","message":"Dev releases are not covered by Drupal security advisories."}},"assets":{"packages":{"dthree":"*","cthree":"*","cthree\/css":"*"}}},"description":"Charts module integration with C3 Charts.","require":{"drupal\/charts":"self.version","dthree":"*","cthree":"*","cthree\/css":"*","drupal\/core":"~8.0"},"repositories":[{"type":"package","package":{"name":"dthree","version":"3","type":"dthree","dist":{"url":"https:\/\/d3js.org\/d3.v3.min.js","type":"file"}}},{"type":"package","package":{"name":"cthree","version":"0.4.11","type":"cthree","dist":{"url":"https:\/\/cdnjs.cloudflare.com\/ajax\/libs\/c3\/0.4.11\/c3.min.js","type":"file"}}},{"type":"package","package":{"name":"cthree\/css","version":"0.4.11","type":"css","dist":{"url":"https:\/\/cdnjs.cloudflare.com\/ajax\/libs\/c3\/0.4.11\/c3.min.css","type":"file"}}}]}}}}