{"packages":{"drupal\/disable_messages":{"dev-1.x":{"keywords":"Actively maintained,Content Display","homepage":"https:\/\/www.drupal.org\/project\/disable_messages","version":"dev-1.x","version_normalized":"dev-1.x","license":"GPL-2.0-or-later","authors":[{"name":"mslabba_zyxware","homepage":"https:\/\/www.drupal.org\/user\/3471683"},{"name":"zyxware","homepage":"https:\/\/www.drupal.org\/user\/222163"}],"support":{"source":"http:\/\/cgit.drupalcode.org\/disable_messages"},"source":{"type":"git","url":"https:\/\/git.drupal.org\/project\/disable_messages","reference":"e63082cef122f703b00bda612c4fb3efb9e1f261"},"type":"drupal-module","uid":"disable_messages-2378747","name":"drupal\/disable_messages","extra":{"branch-alias":{"dev-1.x":"1.x-dev"},"drupal":{"version":"8.x-1.0+9-dev","datestamp":"1470802739","security-coverage":{"status":"not-covered","message":"Dev releases are not covered by Drupal security advisories."}}},"description":"Add options to filter messages shown to the end users","require":{"drupal\/core":"~8.0"}},"1.0.0":{"keywords":"Actively maintained,Content Display","homepage":"https:\/\/www.drupal.org\/project\/disable_messages","version":"1.0.0","version_normalized":"1.0.0.0","license":"GPL-2.0-or-later","authors":[{"name":"mslabba_zyxware","homepage":"https:\/\/www.drupal.org\/user\/3471683"},{"name":"zyxware","homepage":"https:\/\/www.drupal.org\/user\/222163"}],"support":{"source":"http:\/\/cgit.drupalcode.org\/disable_messages"},"source":{"type":"git","url":"https:\/\/git.drupal.org\/project\/disable_messages","reference":"8.x-1.0"},"dist":{"type":"zip","url":"https:\/\/ftp.drupal.org\/files\/projects\/disable_messages-8.x-1.0.zip","reference":"8.x-1.0","shasum":"c12e4cdbad17ed27672e865a09d74d350bb8190d"},"type":"drupal-module","uid":"disable_messages-2775247","name":"drupal\/disable_messages","extra":{"branch-alias":{"dev-1.x":"1.x-dev"},"drupal":{"version":"8.x-1.0","datestamp":"1469787839","security-coverage":{"status":"covered","message":"Covered by Drupal\u0027s security advisory policy"}}},"description":"Add options to filter messages shown to the end users","require":{"drupal\/core":"~8.0"}},"1.0.0-beta1":{"keywords":"Actively maintained,Content Display","homepage":"https:\/\/www.drupal.org\/project\/disable_messages","version":"1.0.0-beta1","version_normalized":"1.0.0.0-beta1","license":"GPL-2.0-or-later","authors":[{"name":"mslabba_zyxware","homepage":"https:\/\/www.drupal.org\/user\/3471683"},{"name":"zyxware","homepage":"https:\/\/www.drupal.org\/user\/222163"}],"support":{"source":"http:\/\/cgit.drupalcode.org\/disable_messages"},"source":{"type":"git","url":"https:\/\/git.drupal.org\/project\/disable_messages","reference":"8.x-1.0-beta1"},"dist":{"type":"zip","url":"https:\/\/ftp.drupal.org\/files\/projects\/disable_messages-8.x-1.0-beta1.zip","reference":"8.x-1.0-beta1","shasum":"00da634f641b38fd9f6dd64fba70e9be163e9e0e"},"type":"drupal-module","uid":"disable_messages-2722253","name":"drupal\/disable_messages","extra":{"branch-alias":{"dev-1.x":"1.x-dev"},"drupal":{"version":"8.x-1.0-beta1","datestamp":"1469787839","security-coverage":{"status":"not-covered","message":"Beta releases are not covered by Drupal security advisories."}}},"description":"Add options to filter messages shown to the end users","require":{"drupal\/core":"~8.0"}}}}}