{"packages":{"drupal\/hellosign":{"dev-1.x":{"keywords":"Actively maintained,Other","homepage":"http:\/\/drupal.org\/project\/hellosign","version":"dev-1.x","version_normalized":"dev-1.x","license":"GPL-2.0+","authors":[{"name":"JKerschner","homepage":"https:\/\/www.drupal.org\/user\/3186295"},{"name":"camprandall","homepage":"https:\/\/www.drupal.org\/user\/1837862"},{"name":"mikeegoulding","homepage":"https:\/\/www.drupal.org\/user\/2867877"}],"support":{"source":"http:\/\/cgit.drupalcode.org\/hellosign"},"source":{"type":"git","url":"https:\/\/git.drupal.org\/project\/hellosign","reference":"307879e67cddfd5439431c7c34ac9c6eb3dc92ee"},"type":"drupal-module","uid":"hellosign-2944529","name":"drupal\/hellosign","extra":{"branch-alias":{"dev-1.x":"1.x-dev"},"drupal":{"version":"8.x-1.0+0-dev","datestamp":"1518562980","security-coverage":{"status":"not-covered","message":"Dev releases are not covered by Drupal security advisories."}}},"description":"Provides functionality for creating and signing eSignatures with the HelloSign API.","require":{"drupal\/core":"*","drupal\/encryption":"^1.0","hellosign\/hellosign-php-sdk":"^3.0"}},"1.0.0":{"keywords":"Actively maintained,Other","homepage":"http:\/\/drupal.org\/project\/hellosign","version":"1.0.0","version_normalized":"1.0.0.0","license":"GPL-2.0+","authors":[{"name":"JKerschner","homepage":"https:\/\/www.drupal.org\/user\/3186295"},{"name":"camprandall","homepage":"https:\/\/www.drupal.org\/user\/1837862"},{"name":"mikeegoulding","homepage":"https:\/\/www.drupal.org\/user\/2867877"}],"support":{"source":"http:\/\/cgit.drupalcode.org\/hellosign"},"source":{"type":"git","url":"https:\/\/git.drupal.org\/project\/hellosign","reference":"8.x-1.0"},"dist":{"type":"zip","url":"https:\/\/ftp.drupal.org\/files\/projects\/hellosign-8.x-1.0.zip","reference":"8.x-1.0","shasum":"7a93f4cb6630fed196a84a5c4f341176588026de"},"type":"drupal-module","uid":"hellosign-2944571","name":"drupal\/hellosign","extra":{"branch-alias":{"dev-1.x":"1.x-dev"},"drupal":{"version":"8.x-1.0","datestamp":"1518562980","security-coverage":{"status":"covered","message":"Covered by Drupal\u0027s security advisory policy"}}},"description":"Provides functionality for creating and signing eSignatures with the HelloSign API.","require":{"drupal\/core":"*","drupal\/encryption":"^1.0","hellosign\/hellosign-php-sdk":"^3.0"}}}}}