{"packages":{"drupal\/transaction":{"dev-1.x":{"keywords":"Actively maintained,Content","homepage":"https:\/\/www.drupal.org\/project\/transaction","version":"dev-1.x","version_normalized":"dev-1.x","license":"GPL-2.0-or-later","authors":[{"name":"manuel.adan","homepage":"https:\/\/www.drupal.org\/user\/516420"}],"support":{"source":"http:\/\/cgit.drupalcode.org\/transaction"},"source":{"type":"git","url":"https:\/\/git.drupal.org\/project\/transaction","reference":"b117322d1e70872b06d48d950eb8f6570b7961fb"},"type":"drupal-module","uid":"transaction-2940415","name":"drupal\/transaction","extra":{"branch-alias":{"dev-1.x":"1.x-dev"},"drupal":{"version":"8.x-1.0-alpha2+17-dev","datestamp":"1520365385","security-coverage":{"status":"not-covered","message":"Project has not opted into security advisory coverage!"}}},"require-dev":{"drupal\/inline_entity_form":"*"},"description":"Transactional operations over entities.","require":{"drupal\/dynamic_entity_reference":"*","drupal\/core":"~8.0"}},"1.0.0-alpha3":{"keywords":"Actively maintained,Content","homepage":"https:\/\/www.drupal.org\/project\/transaction","version":"1.0.0-alpha3","version_normalized":"1.0.0.0-alpha3","license":"GPL-2.0-or-later","authors":[{"name":"manuel.adan","homepage":"https:\/\/www.drupal.org\/user\/516420"}],"support":{"source":"http:\/\/cgit.drupalcode.org\/transaction"},"source":{"type":"git","url":"https:\/\/git.drupal.org\/project\/transaction","reference":"8.x-1.0-alpha3"},"dist":{"type":"zip","url":"https:\/\/ftp.drupal.org\/files\/projects\/transaction-8.x-1.0-alpha3.zip","reference":"8.x-1.0-alpha3","shasum":"4a1859d42a9ca91c6a80f422a2f7ec1cd866307d"},"type":"drupal-module","uid":"transaction-2950572","name":"drupal\/transaction","extra":{"branch-alias":{"dev-1.x":"1.x-dev"},"drupal":{"version":"8.x-1.0-alpha3","datestamp":"1520368084","security-coverage":{"status":"not-covered","message":"Project has not opted into security advisory coverage!"}}},"require-dev":{"drupal\/inline_entity_form":"*"},"description":"Transactional operations over entities.","require":{"drupal\/dynamic_entity_reference":"*","drupal\/core":"~8.0"}},"1.0.0-alpha2":{"keywords":"Actively maintained,Content","homepage":"https:\/\/www.drupal.org\/project\/transaction","version":"1.0.0-alpha2","version_normalized":"1.0.0.0-alpha2","license":"GPL-2.0-or-later","authors":[{"name":"manuel.adan","homepage":"https:\/\/www.drupal.org\/user\/516420"}],"support":{"source":"http:\/\/cgit.drupalcode.org\/transaction"},"source":{"type":"git","url":"https:\/\/git.drupal.org\/project\/transaction","reference":"8.x-1.0-alpha2"},"dist":{"type":"zip","url":"https:\/\/ftp.drupal.org\/files\/projects\/transaction-8.x-1.0-alpha2.zip","reference":"8.x-1.0-alpha2","shasum":"3786a16bce7c478a74e0429ffa124fb17e28c153"},"type":"drupal-module","uid":"transaction-2945186","name":"drupal\/transaction","extra":{"branch-alias":{"dev-1.x":"1.x-dev"},"drupal":{"version":"8.x-1.0-alpha2","datestamp":"1520368084","security-coverage":{"status":"not-covered","message":"Project has not opted into security advisory coverage!"}}},"description":"Transactional operations over entities.","require":{"drupal\/dynamic_entity_reference":"*","drupal\/core":"~8.0"}},"1.0.0-alpha1":{"keywords":"Actively maintained,Content","homepage":"https:\/\/www.drupal.org\/project\/transaction","version":"1.0.0-alpha1","version_normalized":"1.0.0.0-alpha1","license":"GPL-2.0-or-later","authors":[{"name":"manuel.adan","homepage":"https:\/\/www.drupal.org\/user\/516420"}],"support":{"source":"http:\/\/cgit.drupalcode.org\/transaction"},"source":{"type":"git","url":"https:\/\/git.drupal.org\/project\/transaction","reference":"8.x-1.0-alpha1"},"dist":{"type":"zip","url":"https:\/\/ftp.drupal.org\/files\/projects\/transaction-8.x-1.0-alpha1.zip","reference":"8.x-1.0-alpha1","shasum":"c3c5c07dcb639e6624bb7dae3f213522b58c5982"},"type":"drupal-module","uid":"transaction-2943697","name":"drupal\/transaction","extra":{"branch-alias":{"dev-1.x":"1.x-dev"},"drupal":{"version":"8.x-1.0-alpha1","datestamp":"1518732180","security-coverage":{"status":"not-covered","message":"Project has not opted into security advisory coverage!"}}},"description":"Transactional operations over entities.","require":{"drupal\/dynamic_entity_reference":"~1.0","drupal\/core":"~8.0"}}}}}