{"packages":{"drupal\/uc_canadapost":{"dev-2.x":{"keywords":"Actively maintained","homepage":"https:\/\/www.drupal.org\/project\/uc_canadapost","version":"dev-2.x","version_normalized":"dev-2.x","license":"GPL-2.0-or-later","authors":[{"name":"TR","homepage":"https:\/\/www.drupal.org\/user\/202830"}],"support":{"source":"http:\/\/cgit.drupalcode.org\/uc_canadapost"},"source":{"type":"git","url":"https:\/\/git.drupal.org\/project\/uc_canadapost","reference":"c883a72459c98f1aa77a40b9c4c1a139ecdc0514"},"type":"drupal-module","uid":"uc_canadapost-2651858","name":"drupal\/uc_canadapost","extra":{"branch-alias":{"dev-2.x":"2.x-dev"},"drupal":{"version":"8.x-2.x-dev","datestamp":"1453085639","security-coverage":{"status":"not-covered","message":"Dev releases are not covered by Drupal security advisories."}}},"description":"Integration of Canada Post shipping rates tool with Ubercart.","require":{"drupal\/rules":"*","drupal\/uc_quote":"*","drupal\/core":"~8.0"}}}}}