{"packages":{"drupal\/commerce_moodle":{"dev-1.x":{"keywords":"Seeking co-maintainer(s)","homepage":"https:\/\/www.drupal.org\/project\/commerce_moodle","version":"dev-1.x","version_normalized":"dev-1.x","license":"GPL-2.0-or-later","authors":[{"name":"Pere Orga","homepage":"https:\/\/www.drupal.org\/user\/2301194"}],"support":{"source":"http:\/\/cgit.drupalcode.org\/commerce_moodle"},"source":{"type":"git","url":"https:\/\/git.drupal.org\/project\/commerce_moodle","reference":"28cbccfbed028d45382da04f605801dedfe142f0"},"type":"drupal-module","uid":"commerce_moodle-1886012","name":"drupal\/commerce_moodle","extra":{"branch-alias":{"dev-1.x":"1.x-dev"},"drupal":{"version":"7.x-1.3+1-dev","datestamp":"1467836568","security-coverage":{"status":"not-covered","message":"Dev releases are not covered by Drupal security advisories."}}},"description":"Provides Commerce integration with Moodle.","require":{"drupal\/commerce":"*","drupal\/commerce_cart":"*","drupal\/commerce_checkout":"*","drupal\/commerce_line_item":"*","drupal\/commerce_order":"*","drupal\/commerce_product":"*","drupal\/moodle_connector":"*","drupal\/drupal":"~7.0"}},"1.3.0":{"keywords":"Seeking co-maintainer(s)","homepage":"https:\/\/www.drupal.org\/project\/commerce_moodle","version":"1.3.0","version_normalized":"1.3.0.0","license":"GPL-2.0-or-later","authors":[{"name":"Pere Orga","homepage":"https:\/\/www.drupal.org\/user\/2301194"}],"support":{"source":"http:\/\/cgit.drupalcode.org\/commerce_moodle"},"source":{"type":"git","url":"https:\/\/git.drupal.org\/project\/commerce_moodle","reference":"7.x-1.3"},"dist":{"type":"zip","url":"https:\/\/ftp.drupal.org\/files\/projects\/commerce_moodle-7.x-1.3.zip","reference":"7.x-1.3","shasum":"20a1f954e5c8b293d9632642ff4d1fab4b963da5"},"type":"drupal-module","uid":"commerce_moodle-2202635","name":"drupal\/commerce_moodle","extra":{"branch-alias":{"dev-1.x":"1.x-dev"},"drupal":{"version":"7.x-1.3","datestamp":"1393027105","security-coverage":{"status":"covered","message":"Covered by Drupal\u0027s security advisory policy"}}},"require":{"drupal\/drupal":"~7.0"}},"1.2.0":{"keywords":"Seeking co-maintainer(s)","homepage":"https:\/\/www.drupal.org\/project\/commerce_moodle","version":"1.2.0","version_normalized":"1.2.0.0","license":"GPL-2.0-or-later","authors":[{"name":"Pere Orga","homepage":"https:\/\/www.drupal.org\/user\/2301194"}],"support":{"source":"http:\/\/cgit.drupalcode.org\/commerce_moodle"},"source":{"type":"git","url":"https:\/\/git.drupal.org\/project\/commerce_moodle","reference":"7.x-1.2"},"dist":{"type":"zip","url":"https:\/\/ftp.drupal.org\/files\/projects\/commerce_moodle-7.x-1.2.zip","reference":"7.x-1.2","shasum":"5d519f5d363069220bcadd3f156faccb142d7b64"},"type":"drupal-module","uid":"commerce_moodle-2177809","name":"drupal\/commerce_moodle","extra":{"branch-alias":{"dev-1.x":"1.x-dev"},"drupal":{"version":"7.x-1.2","datestamp":"1393027105","security-coverage":{"status":"covered","message":"Covered by Drupal\u0027s security advisory policy"}}},"description":"Provides Commerce integration with Moodle.","require":{"drupal\/commerce":"*","drupal\/commerce_cart":"*","drupal\/commerce_checkout":"*","drupal\/commerce_line_item":"*","drupal\/commerce_order":"*","drupal\/commerce_product":"*","drupal\/moodle_connector":"*","drupal\/drupal":"~7.0"}},"1.1.0":{"keywords":"Seeking co-maintainer(s)","homepage":"https:\/\/www.drupal.org\/project\/commerce_moodle","version":"1.1.0","version_normalized":"1.1.0.0","license":"GPL-2.0-or-later","authors":[{"name":"Pere Orga","homepage":"https:\/\/www.drupal.org\/user\/2301194"}],"support":{"source":"http:\/\/cgit.drupalcode.org\/commerce_moodle"},"source":{"type":"git","url":"https:\/\/git.drupal.org\/project\/commerce_moodle","reference":"7.x-1.1"},"dist":{"type":"zip","url":"https:\/\/ftp.drupal.org\/files\/projects\/commerce_moodle-7.x-1.1.zip","reference":"7.x-1.1","shasum":"8722d1f5a52ceda5af8e70de5861f554b62d478b"},"type":"drupal-module","uid":"commerce_moodle-1969776","name":"drupal\/commerce_moodle","extra":{"branch-alias":{"dev-1.x":"1.x-dev"},"drupal":{"version":"7.x-1.1","datestamp":"1390265005","security-coverage":{"status":"covered","message":"Covered by Drupal\u0027s security advisory policy"}}},"description":"Provides Commerce integration with Moodle.","require":{"drupal\/commerce":"*","drupal\/commerce_cart":"*","drupal\/commerce_checkout":"*","drupal\/commerce_line_item":"*","drupal\/commerce_order":"*","drupal\/commerce_product":"*","drupal\/moodle_connector":"*","drupal\/drupal":"~7.0"}},"1.0.0":{"keywords":"Seeking co-maintainer(s)","homepage":"https:\/\/www.drupal.org\/project\/commerce_moodle","version":"1.0.0","version_normalized":"1.0.0.0","license":"GPL-2.0-or-later","authors":[{"name":"Pere Orga","homepage":"https:\/\/www.drupal.org\/user\/2301194"}],"support":{"source":"http:\/\/cgit.drupalcode.org\/commerce_moodle"},"source":{"type":"git","url":"https:\/\/git.drupal.org\/project\/commerce_moodle","reference":"7.x-1.0"},"dist":{"type":"zip","url":"https:\/\/ftp.drupal.org\/files\/projects\/commerce_moodle-7.x-1.0.zip","reference":"7.x-1.0","shasum":"589589c04933abf3b7444572a377ece51b85042b"},"type":"drupal-module","uid":"commerce_moodle-1873826","name":"drupal\/commerce_moodle","extra":{"branch-alias":{"dev-1.x":"1.x-dev"},"drupal":{"version":"7.x-1.0","datestamp":"1386504205","security-coverage":{"status":"covered","message":"Covered by Drupal\u0027s security advisory policy"}}},"description":"Provides Commerce integration with Moodle.","require":{"drupal\/commerce":"*","drupal\/commerce_cart":"*","drupal\/commerce_checkout":"*","drupal\/commerce_line_item":"*","drupal\/commerce_order":"*","drupal\/commerce_product":"*","drupal\/moodle_connector":"*","drupal\/drupal":"~7.0"}}}}}