{"packages":{"drupal\/docreferences":{"1.0.0-alpha1":{"keywords":"Actively maintained","homepage":"https:\/\/www.drupal.org\/project\/docreferences","version":"1.0.0-alpha1","version_normalized":"1.0.0.0-alpha1","license":"GPL-2.0-or-later","authors":[{"name":"bryanhirsch","homepage":"https:\/\/www.drupal.org\/user\/250093"}],"support":{"source":"http:\/\/cgit.drupalcode.org\/docreferences"},"source":{"type":"git","url":"https:\/\/git.drupal.org\/project\/docreferences","reference":"7.x-1.0-alpha1"},"dist":{"type":"zip","url":"https:\/\/ftp.drupal.org\/files\/projects\/docreferences-7.x-1.0-alpha1.zip","reference":"7.x-1.0-alpha1","shasum":"bccf17269ed02a4ce064303acd2629cc5004607c"},"type":"drupal-module","uid":"docreferences-1431394","name":"drupal\/docreferences","extra":{"branch-alias":{"dev-1.x":"1.x-dev"},"drupal":{"version":"7.x-1.0-alpha1","datestamp":"1328623540","security-coverage":{"status":"not-covered","message":"Project has not opted into security advisory coverage!"}}},"require-dev":{"drupal\/ctools":"*","drupal\/lessons":"*"},"description":"Provide links to reference materials on external websites.","require":{"drupal\/ctools":"*","drupal\/features":"*","drupal\/drupal":"~7.0"}}}}}