{"packages":{"drupal\/domain_tax":{"dev-1.x":{"keywords":"Unsupported,Multisite","homepage":"https:\/\/www.drupal.org\/project\/domain_tax","version":"dev-1.x","version_normalized":"dev-1.x","license":"GPL-2.0-or-later","authors":[{"name":"MrHaroldA","homepage":"https:\/\/www.drupal.org\/user\/168440"}],"support":{"source":"http:\/\/cgit.drupalcode.org\/domain_tax"},"source":{"type":"git","url":"https:\/\/git.drupal.org\/project\/domain_tax","reference":"75777462c3bb9172f82f71a12e42dbc100383038"},"type":"drupal-module","uid":"domain_tax-1450332","name":"drupal\/domain_tax","extra":{"branch-alias":{"dev-1.x":"1.x-dev"},"drupal":{"version":"7.x-1.x-dev","datestamp":"1383685104","security-coverage":{"status":"not-covered","message":"Project has not opted into security advisory coverage!"}}},"description":"Assign taxonomy vocabularies and terms to domains created by the Domain Access module.","require":{"drupal\/domain":"*","drupal\/drupal":"*"}}}}}