{"packages":{"drupal\/dotmailer_signup":{"1.1.0":{"keywords":"Actively maintained,Third-party Integration","homepage":"https:\/\/www.drupal.org\/project\/dotmailer_signup","version":"1.1.0","version_normalized":"1.1.0.0","license":"GPL-2.0-or-later","authors":[{"name":"philipnorton42","homepage":"https:\/\/www.drupal.org\/user\/545978"}],"support":{"source":"http:\/\/cgit.drupalcode.org\/dotmailer_signup"},"source":{"type":"git","url":"https:\/\/git.drupal.org\/project\/dotmailer_signup","reference":"7.x-1.1"},"dist":{"type":"zip","url":"https:\/\/ftp.drupal.org\/files\/projects\/dotmailer_signup-7.x-1.1.zip","reference":"7.x-1.1","shasum":"7654713e9cedf09d9aadca27b55269ea846f4df3"},"type":"drupal-module","uid":"dotmailer_signup-2123259","name":"drupal\/dotmailer_signup","extra":{"branch-alias":{"dev-1.x":"1.x-dev"},"drupal":{"version":"7.x-1.1","datestamp":"1383068730","security-coverage":{"status":"covered","message":"Covered by Drupal\u0027s security advisory policy"}}},"description":"Creates a dotmailer signup form.","require":{"drupal\/dotmailer_integration":"*","drupal\/drupal":"~7.0"}},"1.0.0":{"keywords":"Actively maintained,Third-party Integration","homepage":"https:\/\/www.drupal.org\/project\/dotmailer_signup","version":"1.0.0","version_normalized":"1.0.0.0","license":"GPL-2.0-or-later","authors":[{"name":"philipnorton42","homepage":"https:\/\/www.drupal.org\/user\/545978"}],"support":{"source":"http:\/\/cgit.drupalcode.org\/dotmailer_signup"},"source":{"type":"git","url":"https:\/\/git.drupal.org\/project\/dotmailer_signup","reference":"7.x-1.0"},"dist":{"type":"zip","url":"https:\/\/ftp.drupal.org\/files\/projects\/dotmailer_signup-7.x-1.0.zip","reference":"7.x-1.0","shasum":"99d01cdaa366740fed70a7974baad7950ed03447"},"type":"drupal-module","uid":"dotmailer_signup-2121087","name":"drupal\/dotmailer_signup","extra":{"branch-alias":{"dev-1.x":"1.x-dev"},"drupal":{"version":"7.x-1.0","datestamp":"1382797527","security-coverage":{"status":"covered","message":"Covered by Drupal\u0027s security advisory policy"}}},"description":"Creates a dotmailer signup form.","require":{"drupal\/dotmailer_integration":"*","drupal\/drupal":"~7.0"}}}}}