{"packages":{"drupal\/nginx_securelink":{"dev-2.x":{"keywords":"Actively maintained,Content Access Control","homepage":"https:\/\/www.drupal.org\/project\/nginx_securelink","version":"dev-2.x","version_normalized":"dev-2.x","license":"GPL-2.0-or-later","authors":[{"name":"hejazee","homepage":"https:\/\/www.drupal.org\/user\/911168"}],"support":{"source":"http:\/\/cgit.drupalcode.org\/nginx_securelink"},"source":{"type":"git","url":"https:\/\/git.drupal.org\/project\/nginx_securelink","reference":"ac4b0a9c14f59aa3c6720fae3fefc7612ea5c1d2"},"type":"drupal-module","uid":"nginx_securelink-2801717","name":"drupal\/nginx_securelink","extra":{"branch-alias":{"dev-2.x":"2.x-dev"},"drupal":{"version":"7.x-2.0-alpha2+2-dev","datestamp":"1474559778","security-coverage":{"status":"not-covered","message":"Dev releases are not covered by Drupal security advisories."}}},"require-dev":{"drupal\/views":"*"},"description":"Create and manage secure links for private downloads","require":{"drupal\/drupal":"~7.0"}},"dev-1.x":{"keywords":"Actively maintained,Content Access Control","homepage":"https:\/\/www.drupal.org\/project\/nginx_securelink","version":"dev-1.x","version_normalized":"dev-1.x","license":"GPL-2.0-or-later","authors":[{"name":"hejazee","homepage":"https:\/\/www.drupal.org\/user\/911168"}],"support":{"source":"http:\/\/cgit.drupalcode.org\/nginx_securelink"},"source":{"type":"git","url":"https:\/\/git.drupal.org\/project\/nginx_securelink","reference":"894d4fa7aa15ee388aa899397adf1ae86fa3cdf4"},"type":"drupal-module","uid":"nginx_securelink-2475551","name":"drupal\/nginx_securelink","extra":{"branch-alias":{"dev-1.x":"1.x-dev"},"drupal":{"version":"7.x-1.1+2-dev","datestamp":"1474559778","security-coverage":{"status":"not-covered","message":"Dev releases are not covered by Drupal security advisories."}}},"require-dev":{"drupal\/views":"*"},"description":"Create and manage secure links for private downloads","require":{"drupal\/drupal":"~7.0"}},"2.0.0-alpha2":{"keywords":"Actively maintained,Content Access Control","homepage":"https:\/\/www.drupal.org\/project\/nginx_securelink","version":"2.0.0-alpha2","version_normalized":"2.0.0.0-alpha2","license":"GPL-2.0-or-later","authors":[{"name":"hejazee","homepage":"https:\/\/www.drupal.org\/user\/911168"}],"support":{"source":"http:\/\/cgit.drupalcode.org\/nginx_securelink"},"source":{"type":"git","url":"https:\/\/git.drupal.org\/project\/nginx_securelink","reference":"7.x-2.0-alpha2"},"dist":{"type":"zip","url":"https:\/\/ftp.drupal.org\/files\/projects\/nginx_securelink-7.x-2.0-alpha2.zip","reference":"7.x-2.0-alpha2","shasum":"0a8f465c0a99bcc0ac528c2638260daecca5d245"},"type":"drupal-module","uid":"nginx_securelink-2804213","name":"drupal\/nginx_securelink","extra":{"branch-alias":{"dev-2.x":"2.x-dev"},"drupal":{"version":"7.x-2.0-alpha2","datestamp":"1474499639","security-coverage":{"status":"not-covered","message":"Alpha releases are not covered by Drupal security advisories."}}},"require-dev":{"drupal\/views":"*"},"description":"Create and manage secure links for private downloads","require":{"drupal\/drupal":"~7.0"}},"2.0.0-alpha1":{"keywords":"Actively maintained,Content Access Control","homepage":"https:\/\/www.drupal.org\/project\/nginx_securelink","version":"2.0.0-alpha1","version_normalized":"2.0.0.0-alpha1","license":"GPL-2.0-or-later","authors":[{"name":"hejazee","homepage":"https:\/\/www.drupal.org\/user\/911168"}],"support":{"source":"http:\/\/cgit.drupalcode.org\/nginx_securelink"},"source":{"type":"git","url":"https:\/\/git.drupal.org\/project\/nginx_securelink","reference":"7.x-2.0-alpha1"},"dist":{"type":"zip","url":"https:\/\/ftp.drupal.org\/files\/projects\/nginx_securelink-7.x-2.0-alpha1.zip","reference":"7.x-2.0-alpha1","shasum":"35e17bac82b97bfe713ad990a8cca89cf1d3b1ad"},"type":"drupal-module","uid":"nginx_securelink-2802027","name":"drupal\/nginx_securelink","extra":{"branch-alias":{"dev-2.x":"2.x-dev"},"drupal":{"version":"7.x-2.0-alpha1","datestamp":"1474499639","security-coverage":{"status":"not-covered","message":"Alpha releases are not covered by Drupal security advisories."}}},"require-dev":{"drupal\/views":"*"},"description":"Create and manage secure links for private downloads","require":{"drupal\/drupal":"~7.0"}},"1.1.0":{"keywords":"Actively maintained,Content Access Control","homepage":"https:\/\/www.drupal.org\/project\/nginx_securelink","version":"1.1.0","version_normalized":"1.1.0.0","license":"GPL-2.0-or-later","authors":[{"name":"hejazee","homepage":"https:\/\/www.drupal.org\/user\/911168"}],"support":{"source":"http:\/\/cgit.drupalcode.org\/nginx_securelink"},"source":{"type":"git","url":"https:\/\/git.drupal.org\/project\/nginx_securelink","reference":"7.x-1.1"},"dist":{"type":"zip","url":"https:\/\/ftp.drupal.org\/files\/projects\/nginx_securelink-7.x-1.1.zip","reference":"7.x-1.1","shasum":"b891c9d96b6dcbca7d0bc635621e78b89871b10b"},"type":"drupal-module","uid":"nginx_securelink-2801725","name":"drupal\/nginx_securelink","extra":{"branch-alias":{"dev-1.x":"1.x-dev"},"drupal":{"version":"7.x-1.1","datestamp":"1474115039","security-coverage":{"status":"covered","message":"Covered by Drupal\u0027s security advisory policy"}}},"require-dev":{"drupal\/views":"*"},"description":"Create and manage secure links for private downloads","require":{"drupal\/drupal":"~7.0"}},"1.0.0":{"keywords":"Actively maintained,Content Access Control","homepage":"https:\/\/www.drupal.org\/project\/nginx_securelink","version":"1.0.0","version_normalized":"1.0.0.0","license":"GPL-2.0-or-later","authors":[{"name":"hejazee","homepage":"https:\/\/www.drupal.org\/user\/911168"}],"support":{"source":"http:\/\/cgit.drupalcode.org\/nginx_securelink"},"source":{"type":"git","url":"https:\/\/git.drupal.org\/project\/nginx_securelink","reference":"7.x-1.0"},"dist":{"type":"zip","url":"https:\/\/ftp.drupal.org\/files\/projects\/nginx_securelink-7.x-1.0.zip","reference":"7.x-1.0","shasum":"f6877d14345db8ac7872df506a1045f3f5559818"},"type":"drupal-module","uid":"nginx_securelink-2537440","name":"drupal\/nginx_securelink","extra":{"branch-alias":{"dev-1.x":"1.x-dev"},"drupal":{"version":"7.x-1.0","datestamp":"1474115039","security-coverage":{"status":"covered","message":"Covered by Drupal\u0027s security advisory policy"}}},"description":"Create and manage secure links for private downloads","require":{"drupal\/drupal":"~7.0"}}}}}