{"packages":{"drupal\/purr_messages":{"dev-2.x":{"keywords":"Actively maintained","homepage":"https:\/\/www.drupal.org\/project\/purr_messages","version":"dev-2.x","version_normalized":"dev-2.x","license":"GPL-2.0-or-later","authors":[{"name":"tanc","homepage":"https:\/\/www.drupal.org\/user\/64430"}],"support":{"source":"http:\/\/cgit.drupalcode.org\/purr_messages"},"source":{"type":"git","url":"https:\/\/git.drupal.org\/project\/purr_messages","reference":"6ed755b46cf195a63c717fe0a821ce8ca170df7b"},"type":"drupal-module","uid":"purr_messages-1247208","name":"drupal\/purr_messages","extra":{"branch-alias":{"dev-2.x":"2.x-dev"},"drupal":{"version":"7.x-2.0+1-dev","datestamp":"1313151730","security-coverage":{"status":"not-covered","message":"Project has not opted into security advisory coverage!"}}},"description":"A jQuery based override of Drupal\u0027s core message system","require":{"drupal\/drupal":"~7.0"}},"dev-1.x":{"keywords":"Actively maintained","homepage":"https:\/\/www.drupal.org\/project\/purr_messages","version":"dev-1.x","version_normalized":"dev-1.x","license":"GPL-2.0-or-later","authors":[{"name":"tanc","homepage":"https:\/\/www.drupal.org\/user\/64430"}],"support":{"source":"http:\/\/cgit.drupalcode.org\/purr_messages"},"source":{"type":"git","url":"https:\/\/git.drupal.org\/project\/purr_messages","reference":"dd0c5e96538652c45230bc9733e6165e7f964c50"},"type":"drupal-module","uid":"purr_messages-1128260","name":"drupal\/purr_messages","extra":{"branch-alias":{"dev-1.x":"1.x-dev"},"drupal":{"version":"7.x-1.x-dev","datestamp":"1302869600","security-coverage":{"status":"not-covered","message":"Project has not opted into security advisory coverage!"}}},"description":"A jQuery based override of Drupal\u0027s core message system","require":{"drupal\/drupal":"~7.0"}},"2.0.0-beta3":{"keywords":"Actively maintained","homepage":"https:\/\/www.drupal.org\/project\/purr_messages","version":"2.0.0-beta3","version_normalized":"2.0.0.0-beta3","license":"GPL-2.0-or-later","authors":[{"name":"tanc","homepage":"https:\/\/www.drupal.org\/user\/64430"}],"support":{"source":"http:\/\/cgit.drupalcode.org\/purr_messages"},"source":{"type":"git","url":"https:\/\/git.drupal.org\/project\/purr_messages","reference":"7.x-2.0-beta3"},"dist":{"type":"zip","url":"https:\/\/ftp.drupal.org\/files\/projects\/purr_messages-7.x-2.0-beta3.zip","reference":"7.x-2.0-beta3","shasum":"e4fb300178fe5330cac57a077f84f20340a31a8b"},"type":"drupal-module","uid":"purr_messages-1424138","name":"drupal\/purr_messages","extra":{"branch-alias":{"dev-2.x":"2.x-dev"},"drupal":{"version":"7.x-2.0-beta3","datestamp":"1328098565","security-coverage":{"status":"not-covered","message":"Project has not opted into security advisory coverage!"}}},"description":"A jQuery based override of Drupal\u0027s core message system","require":{"drupal\/drupal":"~7.0"}},"2.0.0-beta2":{"keywords":"Actively maintained","homepage":"https:\/\/www.drupal.org\/project\/purr_messages","version":"2.0.0-beta2","version_normalized":"2.0.0.0-beta2","license":"GPL-2.0-or-later","authors":[{"name":"tanc","homepage":"https:\/\/www.drupal.org\/user\/64430"}],"support":{"source":"http:\/\/cgit.drupalcode.org\/purr_messages"},"source":{"type":"git","url":"https:\/\/git.drupal.org\/project\/purr_messages","reference":"7.x-2.0-beta2"},"dist":{"type":"zip","url":"https:\/\/ftp.drupal.org\/files\/projects\/purr_messages-7.x-2.0-beta2.zip","reference":"7.x-2.0-beta2","shasum":"ebe34289183c43b61b724f7a691ca0eb8bb2ad63"},"type":"drupal-module","uid":"purr_messages-1255812","name":"drupal\/purr_messages","extra":{"branch-alias":{"dev-2.x":"2.x-dev"},"drupal":{"version":"7.x-2.0-beta2","datestamp":"1313964127","security-coverage":{"status":"not-covered","message":"Project has not opted into security advisory coverage!"}}},"description":"A jQuery based override of Drupal\u0027s core message system","require":{"drupal\/drupal":"~7.0"}},"2.0.0-beta1":{"keywords":"Actively maintained","homepage":"https:\/\/www.drupal.org\/project\/purr_messages","version":"2.0.0-beta1","version_normalized":"2.0.0.0-beta1","license":"GPL-2.0-or-later","authors":[{"name":"tanc","homepage":"https:\/\/www.drupal.org\/user\/64430"}],"support":{"source":"http:\/\/cgit.drupalcode.org\/purr_messages"},"source":{"type":"git","url":"https:\/\/git.drupal.org\/project\/purr_messages","reference":"7.x-2.0-beta1"},"dist":{"type":"zip","url":"https:\/\/ftp.drupal.org\/files\/projects\/purr_messages-7.x-2.0-beta1.zip","reference":"7.x-2.0-beta1","shasum":"c358cff9651f6db1f333879a1e6b55b455e6d131"},"type":"drupal-module","uid":"purr_messages-1138246","name":"drupal\/purr_messages","extra":{"branch-alias":{"dev-2.x":"2.x-dev"},"drupal":{"version":"7.x-2.0-beta1","datestamp":"1303775216","security-coverage":{"status":"not-covered","message":"Project has not opted into security advisory coverage!"}}},"description":"A jQuery based override of Drupal\u0027s core message system","require":{"drupal\/drupal":"~7.0"}}}}}