{"packages":{"drupal\/quick_simpletest":{"dev-1.x":{"keywords":"Unsupported","homepage":"https:\/\/www.drupal.org\/project\/quick_simpletest","version":"dev-1.x","version_normalized":"dev-1.x","license":"GPL-2.0-or-later","authors":[{"name":"gellweiler","homepage":"https:\/\/www.drupal.org\/user\/1475838"}],"support":{"source":"http:\/\/cgit.drupalcode.org\/quick_simpletest"},"source":{"type":"git","url":"https:\/\/git.drupal.org\/project\/quick_simpletest","reference":"f3d369ca23b34b0318a81c23e1b5e86cb21e2872"},"type":"drupal-module","uid":"quick_simpletest-1744666","name":"drupal\/quick_simpletest","extra":{"branch-alias":{"dev-1.x":"1.x-dev"},"drupal":{"version":"7.x-1.x-dev","datestamp":"1345682934","security-coverage":{"status":"not-covered","message":"Project has not opted into security advisory coverage!"}}},"description":"Write SimpleTests that perform faster than the original simpleTests.","require":{"drupal\/drupal":"*"}}}}}