{"packages":{"drupal\/simpleflex":{"dev-1.x":{"keywords":"Actively maintained","homepage":"https:\/\/www.drupal.org\/project\/simpleflex","version":"dev-1.x","version_normalized":"dev-1.x","license":"GPL-2.0-or-later","authors":[{"name":"dansologuren","homepage":"https:\/\/www.drupal.org\/user\/858876"},{"name":"xandermar","homepage":"https:\/\/www.drupal.org\/user\/2389578"}],"support":{"source":"http:\/\/cgit.drupalcode.org\/simpleflex"},"source":{"type":"git","url":"https:\/\/git.drupal.org\/project\/simpleflex","reference":"2c4c938605e92ddd897263c6ad8919b3c0e9cd1d"},"type":"drupal-theme","uid":"simpleflex-2865429","name":"drupal\/simpleflex","extra":{"branch-alias":{"dev-1.x":"1.x-dev"},"drupal":{"version":"7.x-1.0+2-dev","datestamp":"1490890083","security-coverage":{"status":"not-covered","message":"Project has not opted into security advisory coverage!"}}},"description":"Simple, light-weight theme for responsive Drupal websites.","require":{"drupal\/drupal":"~7.0"}}}}}