{"packages":{"drupal\/text_with_summary":{"dev-1.x":{"keywords":"Actively maintained","homepage":"https:\/\/www.drupal.org\/project\/text_with_summary","version":"dev-1.x","version_normalized":"dev-1.x","license":"GPL-2.0-or-later","authors":[{"name":"mfb","homepage":"https:\/\/www.drupal.org\/user\/12302"}],"support":{"source":"http:\/\/cgit.drupalcode.org\/text_with_summary"},"source":{"type":"git","url":"https:\/\/git.drupal.org\/project\/text_with_summary","reference":"7.x-1.x"},"type":"drupal-module","uid":"text_with_summary-2853078","name":"drupal\/text_with_summary","extra":{"branch-alias":{"dev-1.x":"1.x-dev"},"drupal":{"version":"7.x-1.0+0-dev","datestamp":"1487219885","security-coverage":{"status":"not-covered","message":"Dev releases are not covered by Drupal security advisories."}}},"description":"Provides a field formatter to display both summary (if it exists) and body of \u0022long text and summary\u0022 fields.","require":{"drupal\/drupal":"*"}},"1.0.0":{"keywords":"Actively maintained","homepage":"https:\/\/www.drupal.org\/project\/text_with_summary","version":"1.0.0","version_normalized":"1.0.0.0","license":"GPL-2.0-or-later","authors":[{"name":"mfb","homepage":"https:\/\/www.drupal.org\/user\/12302"}],"support":{"source":"http:\/\/cgit.drupalcode.org\/text_with_summary"},"source":{"type":"git","url":"https:\/\/git.drupal.org\/project\/text_with_summary","reference":"7.x-1.0"},"dist":{"type":"zip","url":"https:\/\/ftp.drupal.org\/files\/projects\/text_with_summary-7.x-1.0.zip","reference":"7.x-1.0","shasum":"43fc0bfe9165f5420d475c19d364242d763d2e1d"},"type":"drupal-module","uid":"text_with_summary-1222744","name":"drupal\/text_with_summary","extra":{"branch-alias":{"dev-1.x":"1.x-dev"},"drupal":{"version":"7.x-1.0","datestamp":"1311036200","security-coverage":{"status":"covered","message":"Covered by Drupal\u0027s security advisory policy"}}},"description":"Provides a field formatter to display both summary (if it exists) and body of \u0022long text and summary\u0022 fields.","require":{"drupal\/drupal":"*"}}}}}