{"packages":{"drupal\/views_menu_children_filter":{"dev-1.x":{"keywords":"Minimally maintained,Views","homepage":"https:\/\/www.drupal.org\/project\/views_menu_children_filter","version":"dev-1.x","version_normalized":"dev-1.x","license":"GPL-2.0-or-later","authors":[{"name":"bmcclure","homepage":"https:\/\/www.drupal.org\/user\/278485"},{"name":"cravecode","homepage":"https:\/\/www.drupal.org\/user\/1693456"}],"support":{"source":"http:\/\/cgit.drupalcode.org\/views_menu_children_filter"},"source":{"type":"git","url":"https:\/\/git.drupal.org\/project\/views_menu_children_filter","reference":"fc6eace83a2c50f1dd93799418fc39d36b1afd9a"},"type":"drupal-module","uid":"views_menu_children_filter-2482447","name":"drupal\/views_menu_children_filter","extra":{"branch-alias":{"dev-1.x":"1.x-dev"},"drupal":{"version":"7.x-1.0-rc2+13-dev","datestamp":"1498829642","security-coverage":{"status":"not-covered","message":"Project has not opted into security advisory coverage!"}}},"description":"Creates a filter in Views to list a node\u0027s children based on the menu.","require":{"drupal\/views":"*","drupal\/drupal":"~7.0"}},"1.0.0-rc3":{"keywords":"Minimally maintained,Views","homepage":"https:\/\/www.drupal.org\/project\/views_menu_children_filter","version":"1.0.0-rc3","version_normalized":"1.0.0.0-RC3","license":"GPL-2.0-or-later","authors":[{"name":"bmcclure","homepage":"https:\/\/www.drupal.org\/user\/278485"},{"name":"cravecode","homepage":"https:\/\/www.drupal.org\/user\/1693456"}],"support":{"source":"http:\/\/cgit.drupalcode.org\/views_menu_children_filter"},"source":{"type":"git","url":"https:\/\/git.drupal.org\/project\/views_menu_children_filter","reference":"7.x-1.0-rc3"},"dist":{"type":"zip","url":"https:\/\/ftp.drupal.org\/files\/projects\/views_menu_children_filter-7.x-1.0-rc3.zip","reference":"7.x-1.0-rc3","shasum":"97d675f80744caa337bbd7c98e8d0e080cd4ef0c"},"type":"drupal-module","uid":"views_menu_children_filter-2910617","name":"drupal\/views_menu_children_filter","extra":{"branch-alias":{"dev-1.x":"1.x-dev"},"drupal":{"version":"7.x-1.0-rc3","datestamp":"1506012544","security-coverage":{"status":"not-covered","message":"Project has not opted into security advisory coverage!"}}},"description":"Creates a filter in Views to list a node\u0027s children based on the menu.","require":{"drupal\/views":"*","drupal\/drupal":"~7.0"}},"1.0.0-rc2":{"keywords":"Minimally maintained,Views","homepage":"https:\/\/www.drupal.org\/project\/views_menu_children_filter","version":"1.0.0-rc2","version_normalized":"1.0.0.0-RC2","license":"GPL-2.0-or-later","authors":[{"name":"bmcclure","homepage":"https:\/\/www.drupal.org\/user\/278485"},{"name":"cravecode","homepage":"https:\/\/www.drupal.org\/user\/1693456"}],"support":{"source":"http:\/\/cgit.drupalcode.org\/views_menu_children_filter"},"source":{"type":"git","url":"https:\/\/git.drupal.org\/project\/views_menu_children_filter","reference":"7.x-1.0-rc2"},"dist":{"type":"zip","url":"https:\/\/ftp.drupal.org\/files\/projects\/views_menu_children_filter-7.x-1.0-rc2.zip","reference":"7.x-1.0-rc2","shasum":"06a47012e748240e19e673447b6686f3c346894c"},"type":"drupal-module","uid":"views_menu_children_filter-2652266","name":"drupal\/views_menu_children_filter","extra":{"branch-alias":{"dev-1.x":"1.x-dev"},"drupal":{"version":"7.x-1.0-rc2","datestamp":"1506012544","security-coverage":{"status":"not-covered","message":"Project has not opted into security advisory coverage!"}}},"description":"Creates a filter in Views to list a node\u0027s children based on the menu.","require":{"drupal\/views":"*","drupal\/drupal":"~7.0"}},"1.0.0-rc1":{"keywords":"Minimally maintained,Views","homepage":"https:\/\/www.drupal.org\/project\/views_menu_children_filter","version":"1.0.0-rc1","version_normalized":"1.0.0.0-RC1","license":"GPL-2.0-or-later","authors":[{"name":"bmcclure","homepage":"https:\/\/www.drupal.org\/user\/278485"},{"name":"cravecode","homepage":"https:\/\/www.drupal.org\/user\/1693456"}],"support":{"source":"http:\/\/cgit.drupalcode.org\/views_menu_children_filter"},"source":{"type":"git","url":"https:\/\/git.drupal.org\/project\/views_menu_children_filter","reference":"7.x-1.0-rc1"},"dist":{"type":"zip","url":"https:\/\/ftp.drupal.org\/files\/projects\/views_menu_children_filter-7.x-1.0-rc1.zip","reference":"7.x-1.0-rc1","shasum":"63859627d0f82cbd3a8dfbfa23d23d8cd9bd76cb"},"type":"drupal-module","uid":"views_menu_children_filter-2482451","name":"drupal\/views_menu_children_filter","extra":{"branch-alias":{"dev-1.x":"1.x-dev"},"drupal":{"version":"7.x-1.0-rc1","datestamp":"1453139939","security-coverage":{"status":"not-covered","message":"Project has not opted into security advisory coverage!"}}},"description":"Creates a filter in Views to list a node\u0027s children based on the menu.","require":{"drupal\/views":"*","drupal\/drupal":"~7.0"}}}}}