{"packages":{"drupal\/warning":{"dev-1.x":{"keywords":"Actively maintained,Community","homepage":"https:\/\/www.drupal.org\/project\/warning","version":"dev-1.x","version_normalized":"dev-1.x","license":"GPL-2.0-or-later","authors":[{"name":"dag-","homepage":"https:\/\/www.drupal.org\/user\/176957"},{"name":"sdsheridan","homepage":"https:\/\/www.drupal.org\/user\/138669"},{"name":"umangamu","homepage":"https:\/\/www.drupal.org\/user\/2854905"}],"support":{"source":"http:\/\/cgit.drupalcode.org\/warning"},"source":{"type":"git","url":"https:\/\/git.drupal.org\/project\/warning","reference":"bed063e57a5f6321a17cb4500d279dfe7be8524f"},"type":"drupal-module","uid":"warning-2201431","name":"drupal\/warning","extra":{"branch-alias":{"dev-1.x":"1.x-dev"},"drupal":{"version":"7.x-1.1+1-dev","datestamp":"1392911305","security-coverage":{"status":"not-covered","message":"Dev releases are not covered by Drupal security advisories."}}},"description":"Add warning messages to Drupal to discourage certain practices.","require":{"drupal\/drupal":"~7.0"}},"1.1.0":{"keywords":"Actively maintained,Community","homepage":"https:\/\/www.drupal.org\/project\/warning","version":"1.1.0","version_normalized":"1.1.0.0","license":"GPL-2.0-or-later","authors":[{"name":"dag-","homepage":"https:\/\/www.drupal.org\/user\/176957"},{"name":"sdsheridan","homepage":"https:\/\/www.drupal.org\/user\/138669"},{"name":"umangamu","homepage":"https:\/\/www.drupal.org\/user\/2854905"}],"support":{"source":"http:\/\/cgit.drupalcode.org\/warning"},"source":{"type":"git","url":"https:\/\/git.drupal.org\/project\/warning","reference":"7.x-1.1"},"dist":{"type":"zip","url":"https:\/\/ftp.drupal.org\/files\/projects\/warning-7.x-1.1.zip","reference":"7.x-1.1","shasum":"8ea4ca575bebfeafc7e3648d907c16e2b666eaae"},"type":"drupal-module","uid":"warning-2194035","name":"drupal\/warning","extra":{"branch-alias":{"dev-1.x":"1.x-dev"},"drupal":{"version":"7.x-1.1","datestamp":"1392159205","security-coverage":{"status":"covered","message":"Covered by Drupal\u0027s security advisory policy"}}},"description":"Add warning messages to Drupal to discourage certain practices.","require":{"drupal\/drupal":"~7.0"}},"1.0.0":{"keywords":"Actively maintained,Community","homepage":"https:\/\/www.drupal.org\/project\/warning","version":"1.0.0","version_normalized":"1.0.0.0","license":"GPL-2.0-or-later","authors":[{"name":"dag-","homepage":"https:\/\/www.drupal.org\/user\/176957"},{"name":"sdsheridan","homepage":"https:\/\/www.drupal.org\/user\/138669"},{"name":"umangamu","homepage":"https:\/\/www.drupal.org\/user\/2854905"}],"support":{"source":"http:\/\/cgit.drupalcode.org\/warning"},"source":{"type":"git","url":"https:\/\/git.drupal.org\/project\/warning","reference":"7.x-1.0"},"dist":{"type":"zip","url":"https:\/\/ftp.drupal.org\/files\/projects\/warning-7.x-1.0.zip","reference":"7.x-1.0","shasum":"02ab59aa9df9c1b2af03dc2d44696e610eddd3fe"},"type":"drupal-module","uid":"warning-2193897","name":"drupal\/warning","extra":{"branch-alias":{"dev-1.x":"1.x-dev"},"drupal":{"version":"7.x-1.0","datestamp":"1392159205","security-coverage":{"status":"covered","message":"Covered by Drupal\u0027s security advisory policy"}}},"description":"Add warning messages to Drupal to discourage certain practices.","require":{"drupal\/drupal":"~7.0"}}}}}